setup.py
aliyun_api_gateway_sign.egg-info/PKG-INFO
aliyun_api_gateway_sign.egg-info/SOURCES.txt
aliyun_api_gateway_sign.egg-info/dependency_links.txt
aliyun_api_gateway_sign.egg-info/top_level.txt
com/__init__.py
com/aliyun/__init__.py
com/aliyun/api/__init__.py
com/aliyun/api/gateway/__init__.py
com/aliyun/api/gateway/sdk/__init__.py
com/aliyun/api/gateway/sdk/client.py
com/aliyun/api/gateway/sdk/auth/__init__.py
com/aliyun/api/gateway/sdk/auth/md5_tool.py
com/aliyun/api/gateway/sdk/auth/sha_hmac256.py
com/aliyun/api/gateway/sdk/auth/signature_composer.py
com/aliyun/api/gateway/sdk/auth/url_encoder.py
com/aliyun/api/gateway/sdk/common/__init__.py
com/aliyun/api/gateway/sdk/common/constant.py
com/aliyun/api/gateway/sdk/http/__init__.py
com/aliyun/api/gateway/sdk/http/request.py
com/aliyun/api/gateway/sdk/http/response.py
com/aliyun/api/gateway/sdk/util/DateUtil.py
com/aliyun/api/gateway/sdk/util/ParamUtil.py
com/aliyun/api/gateway/sdk/util/UUIDUtil.py
com/aliyun/api/gateway/sdk/util/__init__.py